<?xml version="1.0" encoding="UTF-8" ?>
<!DOCTYPE mapper PUBLIC "-//mybatis.org//DTD Mapper 3.0//EN" 
	"http://mybatis.org/dtd/mybatis-3-mapper.dtd">
<mapper namespace="design">

	<select id="getUser" parameterType="string" resultType="User">
		select
		*
		from user
		where userid=#{userId}
	</select>

	<select id="getUsers" resultType="User">
		select
		*
		from user
		order by lastupdatetime;
	</select>
	
	<insert id="insertUser" parameterType="Design">
		insert into design values(#{designid},#{designname},#{userid},now(),now(),#{price},#{summary})
	</insert>
	
	<delete id="deleteUser" parameterType="string">
		delete from design where
		designid = #{designid}
	</delete>
	
	
	<update id="updateUser" parameterType="Design">
		update design 
		set
		designname = #{designname},
		userid = #{userid},
		lastupdatetime=now(),
		price=#{price},
		summary=#{summary}
		where designid = #{designid}
	</update>

</mapper>
